<?xml version="1.0"?>
<!-- This file is part of the book                 -->
<!--                                               -->
<!--   Abstract Algebra: Theory and Applications   -->
<!--                                               -->
<!-- Copyright (C) 1997-2014  Thomas W. Judson     -->
<!-- See the file COPYING for copying conditions.  -->
<!--                                               -->
<!-- This file is automatically generated from the -->
<!-- private solution manual.  Minor contributed   -->
<!-- edits can be made against this file for       -->
<!-- the purpose of a pull request.                -->
<exercises xml:id="firstlook04-exercises">
    <title>Exercises</title>
	
    <exercise>
        <statement>
            <p>Consider the differential equation
                <me>\frac{dy}{dt} = 3y - 1</me>
            with initial value <m>y(0) = 2</m>.
                <ol>

                    <li>Find the exact solution of the initial value problem.</li>

                    <li>Use Euler's method with step size <m>h = 0.5</m> to approximate the solution to the initial value problem on the interval <m>[0,2]</m>  Your solution should include a table of approximate values of the dependent variable as well as the exact values of the dependent variable.  Make sure that your approximations are accurate to <em>four</em> decimal places.</li>

                    <li>Sketch the graph of the approximate and exact solutions.</li>

                    <li>Use the error bound theorem (Theorem <xref ref="theorem-firstlook04-euler-error-bound"/>) to estimate the error at each approximation.  Your solution should include a table of approximate values of the dependent variable the exact values of the dependent variable, the error estimates, and the actual error.  Make sure that your approximations are accurate to <em>four</em> decimal places.</li>

                </ol></p>
        </statement>
    </exercise>

    <exercise>
        <statement>
            <p>In this series of exercises, we will prove the error bound theorem for Euler's method (Theorem <xref ref="theorem-firstlook04-euler-error-bound"/>).
                <ol>

                    <li>Use Taylor's Theorem to show that for all <m>x \geq -1</m> and any positive <m>m</m>, 
                        <me>0 \leq (1 + x)^m \leq e^{mx}.</me></li>

                    <li>Use part (1) and geometric series to prove the following statement: If <m>s</m> and <m>t</m> are positive real numbers, and <m>\{ a_i \}_{i = 0}^k</m> is a sequence satisfying
                        <md>
                            <mrow>a_0 &amp; \geq -\frac{t}{s}</mrow>
                            <mrow>a_{i+1} &amp; \leq (1 + s) a_i + t, \text{ for }i = 0, 1, 2, \ldots, k,</mrow>
                        </md>
                    then
                        <me>a_{i + 1} \leq e^{(i + 1)s} \left(  \frac{t}{s} + a_0 \right) - \frac{t}{s}.</me></li>

                    <li>When <m>i = 0</m>, <m>y(t_0) = Y_0 = \alpha</m> and the theorem is true.  Use Euler's method and Taylor's Theorem to show that 
                        <me>|y_{i + 1} - Y_{i + 1} | \leq |y_i - Y_i| + h |f(t_i, y_i) - f(t_i, Y_i)| + \frac{h^2}{2} |y''(\xi_i)|</me>
                    where <m>\xi_i \in (t_i, t_{i+1})</m> and <m>y_k = y(t_k)</m>.</li>

                    <li>Show that 
                        <me>|y_{i + 1} - Y_{i + 1} | \leq  |y_i - Y_i| (1 + hL) + \frac{Mh^2}{2}. </me></li>

                    <li>Let <m>a_j = |y_j - Y_j|</m> for <m>j = 0, 1, \ldots, N</m>, <m>s = hL</m>, and <m>t = M h^2/2</m> and apply part (2) to show
                        <me>|y_{i + 1} - Y_{i + 1} | \leq e^{(1 + i)hL} \left(  |y_0 - Y_0| + \frac{M h^2 }{2hL} \right) - \frac{M h^2}{2hL}. </me>
                    and derive that
                        <me>|y_{i + 1} - Y_{i + 1} | \leq \frac{M h }{2L} \left( e^{(t_{i+ 1} - a)L} - 1\right)</me>
                    for each <m>i = 0, 1, \ldots, N-1</m>.</li>

                </ol></p>
        </statement>
        <hint>
        	<p>Hints for part (2):<ul>
                <li>For fixed <m>i</m> show that 
                    <md>
                        <mrow>a_{i + 1} &amp; \leq (1 + s)a_i + t</mrow>
                        <mrow>&amp; \leq (1 + s)[(1 + s)a_{i - 1}+ t] + t</mrow>
                        <mrow>&amp; \leq (1 + s)\{ (1 + s)[(1 + s) a_{i - 2} + t]+ t\} + t</mrow>
                        <mrow>&amp; \vdots</mrow>
                        <mrow>&amp; \leq (1 + s)^{i+1}a_0 + [1 + (1 + s) + (1+s)^2 + \cdots + (1 + s)^i]t.</mrow>
                    </md></li>

                <li>Now use a geometric sum to show that
                    <me>a_{i + 1} \leq (1 + s)^{i + 1} a_0 + \frac{t}{s}[(1 + s)^{i + 1} - 1] = (1 + s)^{i + 1} \left( \frac{t}{s} + a_0 \right) - \frac{t}{s}.</me></li>

                <li>Apply part (1) to derive
                    <me>a_{i + 1} \leq e^{(i + 1)s} \left( \frac{t}{s} + a_0 \right) - \frac{t}{s}.</me></li>

            </ul></p>
        </hint>
    </exercise>


</exercises>
